torch_ard/__init__.py
torch_ard/torch_ard.py
pytorch_ard-0.2.4.dist-info/LICENSE
pytorch_ard-0.2.4.dist-info/METADATA
pytorch_ard-0.2.4.dist-info/WHEEL
pytorch_ard-0.2.4.dist-info/top_level.txt
pytorch_ard-0.2.4.dist-info/RECORD
