Metadata-Version: 2.1
Name: pytorch-ard
Version: 0.2.4
Summary: Make your PyTorch faster
Home-page: https://github.com/HolyBayes/pytorch_ard
Author: Artem Ryzhikov
License: UNKNOWN
Keywords: pytorch,bayesian neural networks,ard,deep learning,neural networks,machine learning
Platform: UNKNOWN
Classifier: Intended Audience :: Science/Research
Classifier: Programming Language :: Python :: 3 
Requires-Dist: torch (>=1.1.0)
Requires-Dist: torchvision (>=0.2.1)
Requires-Dist: scikit-learn (>=0.19.2)
Requires-Dist: pandas
